_gemseo_http_common/__init__.py
_gemseo_http_common/constants.py
_gemseo_http_common/data_conversion.py
_gemseo_http_common/database.py
_gemseo_http_common/models.py
gemseo_http/__init__.py
gemseo_http/_cli.py
gemseo_http/_data_conversion.py
gemseo_http/_files.py
gemseo_http/http_discipline.py
gemseo_http-3.0.0.dist-info/licenses/LICENSE.txt
gemseo_http_server/__init__.py
gemseo_http_server/app.py
gemseo_http_server/cli.py
gemseo_http_server/database.py
gemseo_http_server/gemseo_runner.py
gemseo_http_server/job_creation.py
gemseo_http_server/models.py
gemseo_http_server/security.py
gemseo_http_server/settings.py
gemseo_http_server/utils.py
gemseo_http-3.0.0.dist-info/METADATA
gemseo_http-3.0.0.dist-info/WHEEL
gemseo_http-3.0.0.dist-info/entry_points.txt
gemseo_http-3.0.0.dist-info/top_level.txt
gemseo_http-3.0.0.dist-info/RECORD
