Metadata-Version: 2.4
Name: gemseo-http
Version: 3.0.0
Summary: HTTP Discipline and Server for GEMSEO
Author-email: Jean-Christophe Giret <contact@gemseo.org>
License-Expression: LGPL-3.0
Project-URL: Homepage, https://gemseo.org
Project-URL: Source, https://gitlab.com/gemseo/dev/gemseo-http
Project-URL: Issues, https://gitlab.com/gemseo/dev/gemseo-http/-/issues
Classifier: Intended Audience :: Science/Research
Classifier: Topic :: Scientific/Engineering
Classifier: Operating System :: POSIX :: Linux
Classifier: Operating System :: MacOS
Classifier: Operating System :: Microsoft :: Windows
Classifier: Programming Language :: Python :: 3 :: Only
Classifier: Programming Language :: Python :: 3.10
Classifier: Programming Language :: Python :: 3.11
Classifier: Programming Language :: Python :: 3.12
Classifier: Programming Language :: Python :: 3.13
Requires-Python: <3.14,>=3.10
License-File: LICENSE.txt
Requires-Dist: gemseo[all]<7,>=6
Requires-Dist: httpx<0.28.2,>=0.26
Requires-Dist: numpy
Requires-Dist: pydantic
Requires-Dist: typer<0.16.0,>=0.15.0
Requires-Dist: sqlmodel<0.0.25,>=0.0.20
Requires-Dist: strenum
Provides-Extra: server
Requires-Dist: alembic<1.16.0,>=1.14; extra == "server"
Requires-Dist: fastapi<0.116.0,>=0.114.0; extra == "server"
Requires-Dist: huey<2.5.4,>=2.5.0; extra == "server"
Requires-Dist: pwdlib[argon2]==0.3; extra == "server"
Requires-Dist: pydantic-settings<2.9.2,>=2.0; extra == "server"
Requires-Dist: python-jose<4,>=3.0.0; extra == "server"
Requires-Dist: python-multipart<0.0.21,>=0.0.10; extra == "server"
Requires-Dist: trio<0.31.0,>=0.29.0; extra == "server"
Requires-Dist: uvicorn<0.34.2,>=0.30.0; extra == "server"
Dynamic: license-file
